counter_3bit/counter_3bit.v
module counter_3bit (
  input clk, rst,
  output reg [2:0] count
);

  always @ (posedge clk or negedge clk) begin
    if(rst)
      count <= 3'h0;
    else
      count <= count + 3'h1;
  end   

endmodule

counter_3bit/counter_3bit_tb.v
module counter_3bit_tb;
  reg clk, rst;
  wire [2:0] count;

  counter_3bit c0 (.clk(clk), .rst(rst), .count(count));
  
  initial begin
    $dumpfile("counter_3bit.vcd");
    $dumpvars(0, clk, rst, count);
  end 

  initial begin 
    clk <= 1'b0; rst <= 1'b0;

    #5 rst=~rst;
    #5 rst=~rst;

    #30 $finish;
  end

  initial begin
    forever #5 clk=~clk;
  end

endmodule

counter_3bit/counter_3bit.vcd
$date
	Tue Oct 10 15:19:30 2023
$end
$version
	Icarus Verilog
$end
$timescale
	1s
$end
$scope module counter_3bit_tb $end
$var reg 1 ! clk $end
$upscope $end
$scope module counter_3bit_tb $end
$var reg 1 " rst $end
$upscope $end
$scope module counter_3bit_tb $end
$var wire 3 # count [2:0] $end
$upscope $end
$enddefinitions $end
#0
$dumpvars
bx #
0"
0!
$end
#5
b0 #
1!
1"
#10
b1 #
0!
0"
#15
b10 #
1!
#20
b11 #
0!
#25
b100 #
1!
#30
b101 #
0!
#35
b110 #
1!
#40
b111 #
0!
